pubstomp/__init__.py
pubstomp/cli.py
pubstomp/core.py
pubstomp/gui.py
pubstomp-0.1.9.dist-info/licenses/LICENSE
pubstomp-0.1.9.dist-info/METADATA
pubstomp-0.1.9.dist-info/WHEEL
pubstomp-0.1.9.dist-info/entry_points.txt
pubstomp-0.1.9.dist-info/top_level.txt
pubstomp-0.1.9.dist-info/RECORD
