Metadata-Version: 2.4
Name: pubstomp
Version: 0.1.9
Summary: Advanced async pentesting toolkit with crawling, fuzzing, and reporting
Author-email: Nolan Coe <nolancoe@proton.me>
License-Expression: MIT
Keywords: crawl,pentesting,pentest,cybersecurity,pubstomp,crawler,crawling,fuzz,fuzzer,fuzzing,scanner,scan,xss,nmap,whatweb
Classifier: Environment :: Console
Classifier: Intended Audience :: Information Technology
Classifier: Programming Language :: Python :: 3
Classifier: Topic :: Security
Classifier: Topic :: Software Development :: Libraries :: Python Modules
Classifier: Operating System :: OS Independent
Classifier: Natural Language :: English
Classifier: Development Status :: 3 - Alpha
Requires-Python: >=3.8
License-File: LICENSE
Requires-Dist: aiohttp
Requires-Dist: beautifulsoup4
Requires-Dist: colorama
Requires-Dist: tqdm
Requires-Dist: validators
Dynamic: license-file
